segyrecover/__init__.py
segyrecover/__main__.py
segyrecover/core/_1_image_processor.py
segyrecover/core/_2_amplitude_extractor.py
segyrecover/core/_3_data_processor.py
segyrecover/core/_4_segy_writer.py
segyrecover/core/__init__.py
segyrecover/examples/GEOMETRY/RIV6.geometry
segyrecover/examples/IMAGES/RIV6.tif
segyrecover/examples/PARAMETERS/RIV6.par
segyrecover/examples/ROI/RIV6.roi
segyrecover/examples/SEGY/RIV6.segy
segyrecover/ui/_0_welcome_tab.py
segyrecover/ui/_1_load_image_tab.py
segyrecover/ui/_2_parameters_tab.py
segyrecover/ui/_3_1_roi_selection_logic.py
segyrecover/ui/_3_roi_selection_tab.py
segyrecover/ui/_4_1_digitization_logic.py
segyrecover/ui/_4_2_coords_dialogs.py
segyrecover/ui/_4_digitization_tab.py
segyrecover/ui/_5_1_edit_header.py
segyrecover/ui/_5_2_mute_topography.py
segyrecover/ui/_5_3_agc_rms_dialog.py
segyrecover/ui/_5_4_trace_mixing_dialog.py
segyrecover/ui/_5_results_tab.py
segyrecover/ui/__init__.py
segyrecover/ui/help_dialogs.py
segyrecover/ui/main_window.py
segyrecover/ui/navigation_panel.py
segyrecover/ui/tab_container.py
segyrecover/ui/theme.qss
segyrecover/utils/__init__.py
segyrecover/utils/console_utils.py
segyrecover/utils/resource_utils.py
segyrecover-1.1.2.dist-info/licenses/LICENSE.txt
segyrecover-1.1.2.dist-info/METADATA
segyrecover-1.1.2.dist-info/WHEEL
segyrecover-1.1.2.dist-info/entry_points.txt
segyrecover-1.1.2.dist-info/top_level.txt
segyrecover-1.1.2.dist-info/RECORD
