Metadata-Version: 2.4
Name: segyrecover
Version: 1.1.2
Summary: A Python tool for digitizing scanned seismic reflection sections and converting them to standard SEGY format.
Author-email: Alejandro Pertuz <apertuz@ucm.es>
License: GNU GPL-3.0
Project-URL: Documentation, https://a-pertuz.github.io/REVSEIS/index.html
Project-URL: Source Code, https://github.com/a-pertuz/SEGYRecover
Project-URL: DOI, https://doi.org/10.5281/zenodo.15053412
Keywords: seismic,digitization,segy,geophysics
Classifier: Development Status :: 5 - Production/Stable
Classifier: Intended Audience :: Science/Research
Classifier: License :: OSI Approved :: GNU General Public License v3 (GPLv3)
Classifier: Programming Language :: Python :: 3
Classifier: Programming Language :: Python :: 3.10
Requires-Python: >=3.10
License-File: LICENSE.txt
Requires-Dist: PySide6>=6.8.0
Requires-Dist: matplotlib>=3.8.0
Requires-Dist: numpy>=1.24.0
Requires-Dist: opencv-python>=4.7.0
Requires-Dist: scipy>=1.10.0
Requires-Dist: seisio>=1.2.0
Requires-Dist: seisplot>=1.2.0
Requires-Dist: appdirs>=1.4.4
Requires-Dist: tabulate>=0.9.0
Requires-Dist: setuptools>=65.0.0
Requires-Dist: psutil>=6.0.0
Dynamic: license-file
